streamlit_inspector/__init__.py
streamlit_inspector-0.1.1.dist-info/LICENSE
streamlit_inspector-0.1.1.dist-info/WHEEL
streamlit_inspector-0.1.1.dist-info/METADATA
streamlit_inspector-0.1.1.dist-info/RECORD
